{
 "city": "yum",
 "name": "Yuma (ThreadEx YUMthr 9)",
 "generated": "2026-06-23",
 "facts": [
  {
   "key": "coldest_night",
   "score": 0.631,
   "crossCityPercentile": 0.31,
   "label": "Even the coldest night of the year is warming +1.05\u00b0F per decade",
   "value": 1.05,
   "unit": "\u00b0F/decade",
   "significant": true,
   "rank": 1
  },
  {
   "key": "lows_outpace_highs",
   "score": 0.562,
   "crossCityPercentile": 0.56,
   "label": "Overnight lows are rising 2.1\u00d7 as fast as afternoon highs",
   "value": 2.1,
   "unit": "\u00d7 ratio",
   "significant": true,
   "rank": 2
  },
  {
   "key": "diurnal_compression",
   "score": 0.562,
   "crossCityPercentile": 0.56,
   "label": "The day\u2013night temperature gap is shrinking 0.44\u00b0F per decade",
   "value": 0.44,
   "unit": "\u00b0F/decade",
   "significant": true,
   "rank": 3
  },
  {
   "key": "tropical_nights",
   "score": 0.533,
   "crossCityPercentile": 0.75,
   "label": "70 nights a year now stay at or above 80\u00b0F (was 47 in the 1970s)",
   "value": 70,
   "unit": "nights",
   "baseline": 47,
   "significant": true,
   "rank": 4
  },
  {
   "key": "night_warming",
   "score": 0.532,
   "crossCityPercentile": 0.25,
   "label": "Summer nights are warming +0.84\u00b0F per decade",
   "value": 0.84,
   "unit": "\u00b0F/decade",
   "significant": true,
   "bench": 0.36,
   "rank": 5
  },
  {
   "key": "hot_day_season",
   "score": 0.476,
   "crossCityPercentile": 0.7,
   "label": "115 days a year now reach 100\u00b0F (was 103 in the 1970s)",
   "value": 115,
   "unit": "days",
   "baseline": 103,
   "significant": true,
   "rank": 6
  },
  {
   "key": "night_cooling_share",
   "score": 0.424,
   "crossCityPercentile": 0.29,
   "label": "15% of cooling demand now falls after dark (was 10% in the 1970s)",
   "value": 15,
   "unit": "%",
   "baseline": 10,
   "significant": true,
   "rank": 7
  },
  {
   "key": "urban_excess",
   "score": 0.361,
   "crossCityPercentile": 0.2,
   "label": "City nights are warming +0.28\u00b0F/decade faster than the nearby open desert",
   "value": 0.28,
   "unit": "\u00b0F/decade",
   "significant": true,
   "vs_reference": 0.56,
   "rank": 8
  }
 ]
}